setup.py
screw/__init__.py
screw/shell.py
screw/test.py
screw.egg-info/PKG-INFO
screw.egg-info/SOURCES.txt
screw.egg-info/dependency_links.txt
screw.egg-info/entry_points.txt
screw.egg-info/top_level.txt