Metadata-Version: 1.0
Name: screw
Version: 0.0.3
Summary: screw egg
Home-page: http://yinwentao.com/
Author: yoon
Author-email: yinwentao312@gmail.com
License: MIT License
Keywords: screw,egg
Platform: any
